astrophysix/__init__.py
astrophysix/simdm/__init__.py
astrophysix/simdm/project.py
astrophysix/simdm/study.py
astrophysix/simdm/utils.py
astrophysix/simdm/catalogs/__init__.py
astrophysix/simdm/catalogs/catalog.py
astrophysix/simdm/catalogs/field.py
astrophysix/simdm/catalogs/targobj.py
astrophysix/simdm/d3_web/MathJax_local.js
astrophysix/simdm/d3_web/__init__.py
astrophysix/simdm/d3_web/__main__.py
astrophysix/simdm/d3_web/d3_plot.gif
astrophysix/simdm/d3_web/loading.png
astrophysix/simdm/d3_web/plot.html
astrophysix/simdm/d3_web/plot_no_mathjax.html
astrophysix/simdm/datafiles/__init__.py
astrophysix/simdm/datafiles/datafile.py
astrophysix/simdm/datafiles/file.py
astrophysix/simdm/datafiles/image.py
astrophysix/simdm/datafiles/plot.py
astrophysix/simdm/experiment/__init__.py
astrophysix/simdm/experiment/app_algo.py
astrophysix/simdm/experiment/base.py
astrophysix/simdm/experiment/param_setting.py
astrophysix/simdm/experiment/resolved_physics.py
astrophysix/simdm/protocol/__init__.py
astrophysix/simdm/protocol/algorithm.py
astrophysix/simdm/protocol/base.py
astrophysix/simdm/protocol/input_parameters.py
astrophysix/simdm/protocol/physics.py
astrophysix/simdm/results/__init__.py
astrophysix/simdm/results/generic.py
astrophysix/simdm/results/snapshot.py
astrophysix/simdm/services/__init__.py
astrophysix/simdm/services/process.py
astrophysix/units/__init__.py
astrophysix/units/unit.py
astrophysix/utils/__init__.py
astrophysix/utils/datetime.py
astrophysix/utils/dt_utils.py
astrophysix/utils/file.py
astrophysix/utils/numpy.py
astrophysix/utils/persistency.py
astrophysix/utils/strings.py
astrophysix-0.7.1.dist-info/LICENSE
astrophysix-0.7.1.dist-info/METADATA
astrophysix-0.7.1.dist-info/WHEEL
astrophysix-0.7.1.dist-info/entry_points.txt
astrophysix-0.7.1.dist-info/top_level.txt
astrophysix-0.7.1.dist-info/RECORD
