Metadata-Version: 2.1
Name: astrophysix
Version: 0.7.1
Summary: Astrophysical simulation project documentation package
Home-page: https://astrophysix.readthedocs.io
Author: Damien CHAPON
Author-email: damien.chapon@cea.fr
License: CEA CNRS Inria Logiciel Libre License, version 2.1 (CeCILL-2.1, http://www.cecill.info)
Download-URL: https://gitlab.com/coast-dev/astrophysix
Project-URL: Source, https://drf-gitlab.cea.fr/coast-dev/Astrophysix/
Keywords: Astrophysics simulation analysis publication
Platform: UNKNOWN
Classifier: Intended Audience :: Science/Research
Classifier: License :: OSI Approved :: CEA CNRS Inria Logiciel Libre License, version 2.1 (CeCILL-2.1)
Classifier: Operating System :: MacOS :: MacOS X
Classifier: Operating System :: POSIX :: Linux
Classifier: Development Status :: 5 - Production/Stable
Classifier: Programming Language :: Python :: 2.7
Classifier: Programming Language :: Python :: 3.6
Classifier: Programming Language :: Python :: 3.7
Classifier: Programming Language :: Python :: 3.8
Classifier: Programming Language :: Python :: 3.9
Classifier: Programming Language :: Python :: 3.10
Classifier: Topic :: Software Development :: Version Control :: Git
Classifier: Topic :: Scientific/Engineering :: Physics
Classifier: Topic :: Scientific/Engineering :: Astronomy
Classifier: Topic :: Scientific/Engineering :: Information Analysis
Requires-Python: >=2.7, !=3.0.*, !=3.1.*, !=3.2.*, !=3.3.*, !=3.4.*, <4
License-File: LICENSE
Requires-Dist: Pillow (>=6.2.1)
Requires-Dist: future (>=0.17.1)
Requires-Dist: h5py (>=2.10.0)
Requires-Dist: numpy (>=1.16.4)
Requires-Dist: pandas (>=0.24.2)
Requires-Dist: enum34 ; python_version < "3.4"
Requires-Dist: pytz (>=2019.1) ; python_version < "3.4"
